Metadata-Version: 1.1
Name: ptahcrowd
Version: 0.2
Summary: User management for Ptah.
Home-page: https://github.com/ptahproject/ptahcrowd/
Author: Ptah Project
Author-email: ptahproject@googlegroups.com
License: BSD-derived
Platform: UNKNOWN
Classifier: Intended Audience :: Developers
Classifier: Programming Language :: Python
Classifier: Programming Language :: Python :: 2.6
Classifier: Programming Language :: Python :: 2.7
Classifier: Programming Language :: Python :: 3.2
Classifier: Programming Language :: Python :: Implementation :: CPython
Classifier: Framework :: Pylons
Classifier: Topic :: Internet :: WWW/HTTP
Classifier: Topic :: Internet :: WWW/HTTP :: WSGI
